fast_rub/__init__.py
fast_rub/button/__init__.py
fast_rub/button/key_pad.py
fast_rub/core/__init__.py
fast_rub/core/async_sync.py
fast_rub/core/client.py
fast_rub/network/__init__.py
fast_rub/network/network.py
fast_rub/pyrubi/__init__.py
fast_rub/pyrubi/enums.py
fast_rub/pyrubi/exceptions.py
fast_rub/pyrubi/filters.py
fast_rub/pyrubi/client/__init__.py
fast_rub/pyrubi/client/client.py
fast_rub/pyrubi/crypto/__init__.py
fast_rub/pyrubi/crypto/crypto.py
fast_rub/pyrubi/methods/__init__.py
fast_rub/pyrubi/methods/methods.py
fast_rub/pyrubi/network/__init__.py
fast_rub/pyrubi/network/helper.py
fast_rub/pyrubi/network/network.py
fast_rub/pyrubi/network/socket.py
fast_rub/pyrubi/sessions/__init__.py
fast_rub/pyrubi/sessions/sessions.py
fast_rub/pyrubi/types/__init__.py
fast_rub/pyrubi/types/socket/__init__.py
fast_rub/pyrubi/types/socket/message.py
fast_rub/pyrubi/utils/__init__.py
fast_rub/pyrubi/utils/configs.py
fast_rub/pyrubi/utils/reacrions.py
fast_rub/pyrubi/utils/utils.py
fast_rub/type/__init__.py
fast_rub/type/errors.py
fast_rub/type/file.py
fast_rub/type/get_type.py
fast_rub/type/metadata.py
fast_rub/type/prop_update.py
fast_rub/type/props.py
fast_rub/type/update.py
fast_rub/type/models/__init__.py
fast_rub/type/models/bot.py
fast_rub/type/models/chat.py
fast_rub/types/__init__.py
fast_rub/utils/__init__.py
fast_rub/utils/colors.py
fast_rub/utils/encryption.py
fast_rub/utils/filters.py
fast_rub/utils/logger.py
fast_rub/utils/metadata.py
fast_rub/utils/text_parser.py
fast_rub/utils/utils.py
fast_rub/utils/version.py
fastrub-2.7.5.dist-info/licenses/LICENSE
fastrub-2.7.5.dist-info/METADATA
fastrub-2.7.5.dist-info/WHEEL
fastrub-2.7.5.dist-info/top_level.txt
fastrub-2.7.5.dist-info/RECORD
