Metadata-Version: 2.4
Name: fastrub
Version: 2.7.5
Summary: The fastest library for writing Rubika messenger bots both synchronously and asynchronously ⚡
Home-page: https://github.com/OandONE/fast_rub
Author: seyyed mohamad hosein moosavi raja(01)
Author-email: mohamadhosein159159@gmail.com
License: MIT
Requires-Python: >=3.10
License-File: LICENSE
Requires-Dist: httpx[http2]==0.28.1
Requires-Dist: aiohttp==3.9.0
Requires-Dist: aiofiles==24.1.0
Requires-Dist: filetype
Requires-Dist: mutagen
Requires-Dist: pycryptodome
Requires-Dist: tqdm
Requires-Dist: websocket-client
Dynamic: author
Dynamic: author-email
Dynamic: description
Dynamic: description-content-type
Dynamic: home-page
Dynamic: license
Dynamic: license-file
Dynamic: requires-dist
Dynamic: requires-python
Dynamic: summary
